external_explainers/__init__.py
external_explainers/commons/__init__.py
external_explainers/commons/utils.py
external_explainers/metainsight_explainer/__init__.py
external_explainers/metainsight_explainer/cache.py
external_explainers/metainsight_explainer/data_pattern.py
external_explainers/metainsight_explainer/data_scope.py
external_explainers/metainsight_explainer/meta_insight.py
external_explainers/metainsight_explainer/metainsight_mining.py
external_explainers/metainsight_explainer/pattern_evaluations.py
external_explainers/metainsight_explainer/utils.py
external_explainers/metainsight_explainer/patterns/__init__.py
external_explainers/metainsight_explainer/patterns/outlier_pattern.py
external_explainers/metainsight_explainer/patterns/pattern_base_classes.py
external_explainers/metainsight_explainer/patterns/trend_pattern.py
external_explainers/metainsight_explainer/patterns/unimodality_pattern.py
external_explainers/outlier_explainer/__init__.py
external_explainers/outlier_explainer/outlier_explainer.py
external_explainers-1.0.1.dist-info/licenses/LICENSE
external_explainers-1.0.1.dist-info/METADATA
external_explainers-1.0.1.dist-info/WHEEL
external_explainers-1.0.1.dist-info/top_level.txt
external_explainers-1.0.1.dist-info/RECORD
