Metadata-Version: 2.4
Name: external_explainers
Version: 1.0.1
Project-URL: Git, https://github.com/analysis-bots/ExternalExplainers
License-File: LICENSE
Requires-Dist: wheel
Requires-Dist: pandas>=2.2.3
Requires-Dist: numpy>=2.1.3
Requires-Dist: matplotlib>=3.9.0
Requires-Dist: pymannkendall>=1.4.2
Requires-Dist: scipy>=1.14.1
Requires-Dist: singleton-decorator>=1.0.0
Requires-Dist: scikit-learn>=1.6.0
Requires-Dist: diptest>=0.9.0
Dynamic: description
Dynamic: description-content-type
Dynamic: license-file
Dynamic: project-url
Dynamic: requires-dist
